MeMeST-2024.9.2.data/data/LICENSE
git_tools/__init__.py
git_tools/base_dtypes.py
git_tools/git_api.py
git_tools/rep_task.py
mest/__init__.py
mest/config.py
mest/main.py
mest/rep_mana.py
mest/test_git.py
MeMeST-2024.9.2.dist-info/LICENSE
MeMeST-2024.9.2.dist-info/METADATA
MeMeST-2024.9.2.dist-info/WHEEL
MeMeST-2024.9.2.dist-info/entry_points.txt
MeMeST-2024.9.2.dist-info/top_level.txt
MeMeST-2024.9.2.dist-info/RECORD
