Metadata-Version: 2.1
Name: MeMeST
Version: 2024.9.2
Summary: Multi-Repository Sync Tool
Author: Xin-Xin Ma
License: GPL
Project-URL: Source, https://github.com/xxmawhu/memest.git
License-File: LICENSE
Requires-Dist: termcolor
Requires-Dist: loguru
Requires-Dist: psutil
